rifgenerator/__init__.py
rifgenerator/qrcode.py
rifgenerator-0.1.0.dist-info/licenses/LICENCE
rifgenerator-0.1.0.dist-info/METADATA
rifgenerator-0.1.0.dist-info/WHEEL
rifgenerator-0.1.0.dist-info/top_level.txt
rifgenerator-0.1.0.dist-info/RECORD
