Metadata-Version: 2.4
Name: rifgenerator
Version: 0.1.0
License-File: LICENCE
Requires-Dist: qrcode[pil]
Dynamic: license-file
Dynamic: requires-dist
